shieldsentry/__init__.py
shieldsentry/shieldsentry.py
shieldsentry/specifications.json
shieldsentry-0.0.9.dist-info/LICENSE
shieldsentry-0.0.9.dist-info/METADATA
shieldsentry-0.0.9.dist-info/WHEEL
shieldsentry-0.0.9.dist-info/top_level.txt
shieldsentry-0.0.9.dist-info/RECORD
